{
  "version": 1,
  "sign": "INITIAL_FO",
  "category": "name_initials",
  "language": "en",
  "video_filename": "fo_name_initials_20260415_en_reel.mp4",
  "video_path": "publish_queue/fo_name_initials_20260415_en_reel.mp4",
  "share_to_feed": true,
  "thumb_offset_ms": 4000,
  "posted": false,
  "posted_at": null,
  "instagram_media_id": null,
  "last_error": null,
  "caption": "F and O name people, your cosmic energies are about to UNLEASH a game-changing truth about your true nature.\n\nYou possess an untamed creativity and charisma that magnetizes people to your inner circle.\nYour hidden strength lies in your ability to balance logic and intuition, making you a master problem-solver.\nBe cautious of your tendency to overthink and analyze, as it may lead to mental fatigue and indecision.\n\nYou're a fearless free spirit with a wild heart and a thirst for adventure.\n\nShare this with your fellow F and O name friends who need to know their cosmic secrets!\n\nMusic provided by sonican (https://pixabay.com/users/sonican-38947841/)\n\n#nameinitials #astrology #zodiac #cosmic #fo",
  "script": {
    "hook": "F and O name people, your cosmic energies are about to UNLEASH a game-changing truth about your true nature.",
    "insights": [
      "You possess an untamed creativity and charisma that magnetizes people to your inner circle.",
      "Your hidden strength lies in your ability to balance logic and intuition, making you a master problem-solver.",
      "Be cautious of your tendency to overthink and analyze, as it may lead to mental fatigue and indecision.",
      "The universe is urging you to take bold action towards your passions and desires, no matter how daunting they may seem.",
      "In love, you crave intellectual connection and deep conversations that stimulate your mind and spark your creativity."
    ],
    "personality_trait": "You're a fearless free spirit with a wild heart and a thirst for adventure.",
    "lucky_pairing": "You match best with the bold and confident A and L initials.",
    "lucky_number": 5,
    "lucky_color": "Vibrant Coral",
    "vibe_word": "REBEL",
    "cta": "Share this with your fellow F and O name friends who need to know their cosmic secrets!",
    "genre": "name_initials",
    "subject": "F & O",
    "sign": "INITIAL_FO",
    "lang": "en",
    "date": "April 15, 2026",
    "letters": [
      "F",
      "O"
    ],
    "soundtrack_credit": "Music provided by sonican (https://pixabay.com/users/sonican-38947841/)"
  },
  "created_at": "2026-04-14T20:07:56.535284+00:00"
}